magic_clamp/__init__.py
magic_clamp/autograd.py
magic_clamp/core.py
magic_clamp/project.py
magic_clamp-0.0.4.dist-info/METADATA
magic_clamp-0.0.4.dist-info/WHEEL
magic_clamp-0.0.4.dist-info/top_level.txt
magic_clamp-0.0.4.dist-info/RECORD
