Metadata-Version: 2.1
Name: magic_clamp
Version: 0.0.4
Summary: Magic clamp with conditional straight-through estimator for PyTorch
Author-email: Ben Hayes <ben@benhayes.net>
